bertdotsshutil/__init__.py
bertdotsshutil/client.py
bertdotsshutil/dictutils.py
bertdotsshutil/invocation.py
bertdotsshutil/logger.py
bertdotsshutil/provider.py
bertdotsshutil/scp.py
bertdotsshutil/sync.py
bertdotsshutil-1.1.2.dist-info/METADATA
bertdotsshutil-1.1.2.dist-info/WHEEL
bertdotsshutil-1.1.2.dist-info/top_level.txt
bertdotsshutil-1.1.2.dist-info/RECORD
