Metadata-Version: 2.1
Name: bertdotsshutil
Version: 1.1.2
Summary: Utility library for command invocation via ssh
Home-page: https://github.com/berttejeda/bert.sshutil.git
Author: Engelbert Tejeda
Author-email: berttejeda@gmail.com
License: UNKNOWN
Keywords: ssh,command,python,invoke,remote,invocation
Platform: UNKNOWN
Classifier: Development Status :: 3 - Alpha
Classifier: Intended Audience :: Developers
Classifier: Intended Audience :: Information Technology
Classifier: License :: OSI Approved :: MIT License
Classifier: Natural Language :: English
Classifier: Programming Language :: Python :: 3.7
Requires-Python: >=3.7
Requires-Dist: paramiko (==2.7.0)
Provides-Extra: tests
Requires-Dist: pytest ; extra == 'tests'
Requires-Dist: pytest-cov ; extra == 'tests'
Requires-Dist: coveralls ; extra == 'tests'
Requires-Dist: flake8 ; extra == 'tests'
Requires-Dist: mypy ; extra == 'tests'
